auth0_ai/__init__.py
auth0_ai/authorizers/__init__.py
auth0_ai/authorizers/async_authorization/__init__.py
auth0_ai/authorizers/async_authorization/async_authorization_request.py
auth0_ai/authorizers/async_authorization/async_authorizer_base.py
auth0_ai/authorizers/async_authorization/async_authorizer_params.py
auth0_ai/authorizers/context.py
auth0_ai/authorizers/fga_authorizer.py
auth0_ai/authorizers/token_vault_authorizer.py
auth0_ai/authorizers/types.py
auth0_ai/credentials.py
auth0_ai/interrupts/__init__.py
auth0_ai/interrupts/async_authorization_interrupts.py
auth0_ai/interrupts/auth0_interrupt.py
auth0_ai/interrupts/token_vault_interrupt.py
auth0_ai/stores/__init__.py
auth0_ai/stores/impl/fs_store.py
auth0_ai/stores/impl/in_memory_store.py
auth0_ai/stores/store.py
auth0_ai/stores/sub_store.py
auth0_ai/utils.py
auth0_ai-1.0.2.dist-info/LICENSE
auth0_ai-1.0.2.dist-info/METADATA
auth0_ai-1.0.2.dist-info/WHEEL
auth0_ai-1.0.2.dist-info/RECORD
