Metadata-Version: 2.3
Name: auth0-ai
Version: 1.0.2
Summary: This package provides base abstractions for authentication and authorization in AI applications.
License: Apache-2.0
Author: Auth0
Author-email: support@auth0.com
Requires-Python: >=3.11,<4.0
Classifier: License :: OSI Approved :: Apache Software License
Classifier: Programming Language :: Python :: 3
Classifier: Programming Language :: Python :: 3.11
Classifier: Programming Language :: Python :: 3.12
Classifier: Programming Language :: Python :: 3.13
Requires-Dist: auth0-python (>=4.13.0,<5.0.0)
Requires-Dist: openfga-sdk (>=0.9.5,<0.10.0)
Project-URL: Homepage, https://auth0.com
